{
  "_projectInfo": {
    "file": "light.json",
    "description": "Light Theme",
    "author": "Eltryus - Ricardo Marques",
    "see": "https://github.com/RicardoJCMarques/EasyTrace5000",
    "license": "AGPL-3.0-or-later",
    "copyright": "Copyright (C) 2025-2026 Eltryus - Ricardo Marques"
  },

  "version": "0.1",
  
  "id": "light",
  "colors": {
    "background": {
      "primary": "#ffffff",
      "secondary": "#f8f9fa",
      "tertiary": "#f0f2f5",
      "hover": "#e8eaed",
      "active": "#d0d3d8"
    },
    "text": {
      "primary": "#1a1a1a",
      "secondary": "#666666",
      "disabled": "#999999",
      "hint": "#b0b0b0"
    },
    "border": {
      "primary": "#e0e0e0",
      "secondary": "#d0d0d0",
      "focus": "#4080ff"
    },
    "accent": {
      "primary": "#2563eb",
      "hover": "#1d4ed8",
      "active": "#1e40af"
    },
    "semantic": {
      "success": "#22c55e",
      "warning": "#f59e0b",
      "error": "#ef4444",
      "info": "#06b6d4"
    },
    "operations": {
      "isolation": "#cc6600",
      "drill": "#0066cc",
      "clearing": "#008844",
      "cutout": "#ff00ff",
      "stencil": "#7c3aed",
      "toolpath": "#ff8844"
    },
    "canvas": {
      "background": "#cdcdcd",
      "grid": "#373737",
      "origin": "#373737",
      "originOutline": "#ffffff",
      "bounds": "#373737",
      "ruler": "373737",
      "rulerText": "#373737"
    },
    "geometry": {
      "source": {
        "isolation": "#ff8844",
        "drill": "#4488ff",
        "clearing": "#44ff88",
        "cutout": "#444444",
        "stencil": "#860694"
      },
      "offset": {
        "external": "#a60000",
        "internal": "#00a600",
        "on": "#bcbc02"
      },
      "preview": "#0060dd",
      "toolpath": "#00ffff",
      "selection": "#00ffff",
      "laser": {
        "filled": "#0060dd"
      }
    },
    
    "primitives": {
      "offsetInternal": "#00aa00",
      "offsetExternal": "#ff0000",
      "peckMarkGood": "#16d329ff",
      "peckMarkWarn": "#d2cb00ff",
      "peckMarkError": "#ff0000",
      "peckMarkSlow": "#ff5e00ff",
      "reconstructed": "#00ffff",
      "reconstructedPath": "#ffff00",
      "debugContourColors": ["#00ff00", "#ff0000", "#0000ff", "#ffff00", "#ff00ff", "#00ffff"],
      "debugCurveColors": ["#ff0000", "#00ff00", "#0000ff", "#ffff00", "#ff00ff", "#00ffff"],
      "debugLabel": "#FFFFFF",
      "debugLabelStroke": "#000000"
    },
    "debug": {
      "points": "#ff00ff",
      "arcs": "#00ffff",
      "wireframe": "#00aa00",
      "bounds": "#ff0000"
    },
    "bw":{
      "black": "#000000",
      "white": "#ffffff"
    },
    "pipelines": {
      "cnc": "#cc6600",
      "laser": "#9333ea"
    },
    "interaction": {
      "sponsorship": "#4f46e5",
      "sponsorshipText": "#5b21b6",
      "kofi": "#0d9488"
    }
  }
}